{
  "id": "eley-tenex-air-4-50",
  "url": "https://eley.co.uk/eley-tenex-air-4-50/",
  "category": "air-pellet",
  "name": "ELEY tenex air 4.50",
  "subname": "competition air pellets",
  "specification": [
    {
      "id": "pellet-profile",
      "values": [
        "Flat-head"
      ]
    },
    {
      "id": "pellet-weight",
      "values": [
        "0.531",
        "8.2"
      ],
      "units": [
        "grams",
        "grains"
      ]
    },
    {
      "id": "available-diameters",
      "values": [
        "4.49",
        "4.50",
        "4.51"
      ],
      "units": [
        "mm",
        "mm",
        "mm"
      ]
    },
    {
      "id": "weight-control",
      "values": [
        "30% superior to other brands"
      ]
    },
    {
      "id": "packaging",
      "values": [
        "Damage resistant, re-sealable"
      ]
    }
  ],
  "imageUrl": "https://eley.co.uk/wp-content/uploads/ELEY_tenex_air_4.50.png"
}
